ibis_sqlflite/__init__.py
ibis_sqlflite/converter.py
ibis_sqlflite-0.0.2.dist-info/LICENSE
ibis_sqlflite-0.0.2.dist-info/METADATA
ibis_sqlflite-0.0.2.dist-info/WHEEL
ibis_sqlflite-0.0.2.dist-info/entry_points.txt
ibis_sqlflite-0.0.2.dist-info/top_level.txt
ibis_sqlflite-0.0.2.dist-info/RECORD
