Metadata-Version: 2.1
Name: ibis-sqlflite
Version: 0.0.2
Summary: An Ibis backend for SQLFlite
Author-email: Philip Moore <prmoore77@hotmail.com>
License: Apache License
Project-URL: Homepage, https://github.com/prmoore77/ibis-sqlflite
Keywords: ibis,sqlflite,ibis-framework
Classifier: License :: OSI Approved :: Apache Software License
Classifier: Programming Language :: Python
Classifier: Programming Language :: Python :: 3
Requires-Python: >=3.9
License-File: LICENSE
Requires-Dist: duckdb==1.1.0
Requires-Dist: adbc-driver-flightsql
Requires-Dist: ibis-framework==9.5
Requires-Dist: pyarrow
Requires-Dist: pyarrow-hotfix
Requires-Dist: numpy
Requires-Dist: pandas
Requires-Dist: rich
Provides-Extra: dev
Requires-Dist: bumpver; extra == "dev"
Provides-Extra: test
Requires-Dist: pytest; extra == "test"
Requires-Dist: pytest-snapshot; extra == "test"
Requires-Dist: pytest-mock; extra == "test"
Requires-Dist: filelock; extra == "test"
Requires-Dist: duckdb; extra == "test"
Requires-Dist: dask; extra == "test"
Requires-Dist: distributed; extra == "test"
Requires-Dist: pins[gcs]; extra == "test"
Requires-Dist: docker; extra == "test"
